visionscript/__init__.py
visionscript/cloud.py
visionscript/error_handling.py
visionscript/grammar.py
visionscript/lang.py
visionscript/notebook.py
visionscript/paper_ocr_correction.py
visionscript/registry.py
visionscript/rf_models.py
visionscript/state.py
visionscript/usage.py
visionscript-0.0.7.data/data/visionscript/reference.json/reference.json
visionscript-0.0.7.dist-info/LICENSE
visionscript-0.0.7.dist-info/METADATA
visionscript-0.0.7.dist-info/WHEEL
visionscript-0.0.7.dist-info/entry_points.txt
visionscript-0.0.7.dist-info/top_level.txt
visionscript-0.0.7.dist-info/RECORD
