Metadata-Version: 2.1
Name: visionscript
Version: 0.0.7
Summary: VisionScript is an abstract programming language for doing common computer vision tasks, fast.
Home-page: https://github.com/capjamesg/visionscript
Author: capjamesg
Author-email: jamesg@jamesg.blog
Classifier: Programming Language :: Python :: 3
Classifier: License :: OSI Approved :: MIT License
Classifier: Operating System :: OS Independent
Requires-Python: >=3.7
License-File: LICENSE
Requires-Dist: lark
Requires-Dist: pyspellchecker
Requires-Dist: supervision
Requires-Dist: numpy
Requires-Dist: Pillow
Requires-Dist: requests
Requires-Dist: ultralytics
Requires-Dist: autodistill
Requires-Dist: autodistill-grounded-sam
Requires-Dist: autodistill-blip
Requires-Dist: autodistill-vit
Requires-Dist: click
Requires-Dist: validators
Requires-Dist: werkzeug
Requires-Dist: faiss-cpu
Requires-Dist: torch
Requires-Dist: easyocr
Requires-Dist: scikit-learn
Requires-Dist: webcolors
Requires-Dist: transformers ==4.30.2
Requires-Dist: matplotlib
Requires-Dist: watchdog
Requires-Dist: qrcode
Requires-Dist: flask
Requires-Dist: cryptography
Requires-Dist: pygtrie
Provides-Extra: dev
Requires-Dist: flake8 ; extra == 'dev'
Requires-Dist: black ==22.3.0 ; extra == 'dev'
Requires-Dist: isort ; extra == 'dev'
Requires-Dist: twine ; extra == 'dev'
Requires-Dist: pytest ; extra == 'dev'
Requires-Dist: wheel ; extra == 'dev'
